{
  "main": {
    "id": "5ac1ae7b32980875",
    "type": "split",
    "children": [
      {
        "id": "ba1857dd98bb3b9d",
        "type": "tabs",
        "children": [
          {
            "id": "763395b52758b98f",
            "type": "leaf",
            "state": {
              "type": "markdown",
              "state": {
                "file": "02-Areas/Autoalt/🕎 00 - Hundred Alts.md",
                "mode": "source",
                "source": false
              }
            }
          },
          {
            "id": "eb881394c71ebd51",
            "type": "leaf",
            "state": {
              "type": "markdown",
              "state": {
                "file": "03-Resources/UsefulCommands/commands.md",
                "mode": "source",
                "source": false
              }
            }
          },
          {
            "id": "db03aba6713b866f",
            "type": "leaf",
            "state": {
              "type": "markdown",
              "state": {
                "file": "01-Projects/Semantic Layer/RECO-1617 - Create Metrics using HundredAlts as example.md",
                "mode": "source",
                "source": false
              }
            }
          }
        ],
        "currentTab": 1
      }
    ],
    "direction": "vertical"
  },
  "left": {
    "id": "275fb0f08b4641f5",
    "type": "split",
    "children": [
      {
        "id": "9ac6e034203aca8d",
        "type": "tabs",
        "children": [
          {
            "id": "fe8c9cf9a223fe98",
            "type": "leaf",
            "state": {
              "type": "file-explorer",
              "state": {
                "sortOrder": "alphabetical"
              }
            }
          },
          {
            "id": "074a8585c529a653",
            "type": "leaf",
            "state": {
              "type": "search",
              "state": {
                "query": "seman",
                "matchingCase": false,
                "explainSearch": false,
                "collapseAll": false,
                "extraContext": false,
                "sortOrder": "alphabetical"
              }
            }
          },
          {
            "id": "23a1a3b9214373f2",
            "type": "leaf",
            "state": {
              "type": "bookmarks",
              "state": {}
            }
          }
        ]
      }
    ],
    "direction": "horizontal",
    "width": 415.5
  },
  "right": {
    "id": "7657dc6e4ee19ae7",
    "type": "split",
    "children": [
      {
        "id": "3e2b32569d694402",
        "type": "tabs",
        "children": [
          {
            "id": "cb74ad04fbf6e6ba",
            "type": "leaf",
            "state": {
              "type": "calendar",
              "state": {}
            }
          },
          {
            "id": "bd9a6210cd59b1e4",
            "type": "leaf",
            "state": {
              "type": "backlink",
              "state": {
                "file": "03-Resources/UsefulCommands/commands.md",
                "collapseAll": false,
                "extraContext": false,
                "sortOrder": "alphabetical",
                "showSearch": false,
                "searchQuery": "",
                "backlinkCollapsed": false,
                "unlinkedCollapsed": true
              }
            }
          },
          {
            "id": "a33616f6b1a2a788",
            "type": "leaf",
            "state": {
              "type": "outgoing-link",
              "state": {
                "file": "03-Resources/UsefulCommands/commands.md",
                "linksCollapsed": false,
                "unlinkedCollapsed": true
              }
            }
          },
          {
            "id": "f46aeb2ad2a04f4e",
            "type": "leaf",
            "state": {
              "type": "tag",
              "state": {
                "sortOrder": "frequency",
                "useHierarchy": true
              }
            }
          },
          {
            "id": "62b24d625efbc9f1",
            "type": "leaf",
            "state": {
              "type": "all-properties",
              "state": {
                "sortOrder": "frequency",
                "showSearch": false,
                "searchQuery": ""
              }
            }
          },
          {
            "id": "bf050af3cd1100bf",
            "type": "leaf",
            "state": {
              "type": "outline",
              "state": {
                "file": "03-Resources/UsefulCommands/commands.md"
              }
            }
          }
        ]
      }
    ],
    "direction": "horizontal",
    "width": 432.5
  },
  "left-ribbon": {
    "hiddenItems": {
      "obsidian-excalidraw-plugin:Create new drawing": false,
      "terminal:Open terminal": false,
      "templater-obsidian:Templater": false,
      "obsidian-projects:Open projects": false,
      "obsidian42-brat:BRAT": false,
      "obsidian-day-planner:Timeline": false,
      "switcher:Open quick switcher": false,
      "graph:Open graph view": false,
      "canvas:Create new canvas": false,
      "daily-notes:Open today's daily note": false,
      "templates:Insert template": false,
      "command-palette:Open command palette": false
    }
  },
  "active": "eb881394c71ebd51",
  "lastOpenFiles": [
    "02-Areas/Autoalt/files/HybridSolution.svg",
    "02-Areas/Autoalt/🕎 00 - Hundred Alts.md",
    "02-Areas/Autoalt/🕎 00 - Semantic Layer.md",
    "02-Areas/DailyNotes/2024-04-11.md",
    "02-Areas/DailyNotes/2024-04-10.md",
    "01-Projects/Semantic Layer/RECO-1617 - Create Metrics using HundredAlts as example.md",
    "03-Resources/Obsidian Resources.md",
    "02-Areas/SearchHistorySuggester 1/🎯 Design.md",
    "01-Projects/DevOps/RECO-1607 - Add Kubernetes Probes - Autoalts.md",
    "01-Projects/DevOps/🎯 RECO-1587 - HTTP 503 API Bug.md",
    "01-Projects/Hundred Alts/RECO-1625 Deploy to Superusers.md",
    "02-Areas/DailyNotes/2024-04-02.md",
    "02-Areas/DevOps/🎯 RECO-1591 - Adult DAG Parallelization.md",
    "01-Projects/Semantic Layer",
    "01-Projects/Hundred Alts/RECO-1616 - Prepare AB Metrics.md",
    "01-Projects/Hundred Alts/07- RECO-1513 Final adjustments.md",
    "02-Areas/Systems/🕎 00 - ToBQ.md",
    "02-Areas/Systems/DBT Canvas.canvas",
    "02-Areas/Systems/🕎 00 - DBT.md",
    "02-Areas/Autoalt/🕎 00 - SearchHistorySuggester.md",
    "01-Projects/Sprint/41 - Sprint.md",
    "01-Projects/Sprint",
    "02-Areas/DevOps/🎯  RECO-1590 - ToBQ Partition Filter support.md",
    "00-Inbox/Reading List.md",
    "02-Areas/DailyNotes/2024-04-01.md",
    "02-Areas/DailyNotes/2024-04-29.md",
    "02-Areas/DailyNotes/2024-04-26.md",
    "02-Areas/DailyNotes/2024-04-27.md",
    "02-Areas/Systems/🕎 00 - Streamset.md"
  ]
}